tests/test_options.py
tests/__init__.py
tests/test_memtable.py
tests/test_db.py
rocksdb/_rocksdb.cpython-38-x86_64-linux-gnu.so
rocksdb/interfaces.py
rocksdb/errors.py
rocksdb/merge_operators.py
rocksdb/__init__.py
lbry_rocksdb_optimized-0.8.1.dist-info/LICENSE.md
lbry_rocksdb_optimized-0.8.1.dist-info/top_level.txt
lbry_rocksdb_optimized-0.8.1.dist-info/RECORD
lbry_rocksdb_optimized-0.8.1.dist-info/METADATA
lbry_rocksdb_optimized-0.8.1.dist-info/WHEEL
