Metadata-Version: 2.1
Name: lbry-rocksdb-optimized
Version: 0.8.1
Summary: Python bindings for RocksDB
Home-page: https://github.com/binh-vu/lbry-rocksdb
Author: Binh Vu
Author-email: binh@toan2.com
License: BSD License
Keywords: rocksdb,static,build
Platform: UNKNOWN
Requires-Python: >=3.7.0
License-File: LICENSE.md
Requires-Dist: setuptools (>=25)
Provides-Extra: doc
Requires-Dist: sphinx-rtd-theme ; extra == 'doc'
Requires-Dist: sphinx ; extra == 'doc'
